model_catalogs/__init__.py
model_catalogs/_version.py
model_catalogs/model_catalogs.py
model_catalogs/process.py
model_catalogs/utils.py
model_catalogs/support_files/transform.yaml
model_catalogs/tests/conftest.py
model_catalogs/tests/test_catalog_inputs.py
model_catalogs/tests/test_catalogs.py
model_catalogs-0.7.0.dist-info/LICENSE.txt
model_catalogs-0.7.0.dist-info/METADATA
model_catalogs-0.7.0.dist-info/WHEEL
model_catalogs-0.7.0.dist-info/top_level.txt
model_catalogs-0.7.0.dist-info/RECORD
