Metadata-Version: 2.1
Name: model-catalogs
Version: 0.7.0
Summary: Catalogs for known models
Home-page: https://github.com/NOAA-ORR-ERD/model_catalogs
Author: Kristen Thyng
Author-email: kristen@axds.co
License: MIT
Classifier: Development Status :: 5 - Production/Stable
Classifier: Topic :: Scientific/Engineering
Classifier: Intended Audience :: Science/Research
Classifier: Operating System :: OS Independent
Classifier: Programming Language :: Python
Classifier: Programming Language :: Python :: 3
Classifier: Programming Language :: Python :: 3.7
Classifier: Programming Language :: Python :: 3.8
Classifier: Programming Language :: Python :: 3.9
Classifier: Programming Language :: Python :: 3.10
Classifier: License :: OSI Approved :: MIT License
Requires-Python: >=3.7
License-File: LICENSE.txt
Requires-Dist: appdirs
Requires-Dist: cf-xarray
Requires-Dist: dask
Requires-Dist: datetimerange
Requires-Dist: intake (>=0.6.7)
Requires-Dist: intake-xarray
Requires-Dist: mc-goods
Requires-Dist: netcdf4
Requires-Dist: numpy
Requires-Dist: pandas
Requires-Dist: pip
Requires-Dist: requests
Requires-Dist: siphon
Requires-Dist: xarray
